apibox/__init__.py
apibox/httpstat.py
apibox/log.py
apibox/object.py
apibox/testing.py
apibox/utils.py
apibox-0.2.0.dist-info/DESCRIPTION.rst
apibox-0.2.0.dist-info/METADATA
apibox-0.2.0.dist-info/RECORD
apibox-0.2.0.dist-info/WHEEL
apibox-0.2.0.dist-info/metadata.json
apibox-0.2.0.dist-info/top_level.txt
